Metadata-Version: 1.0
Name: shorttexts
Version: 1.0
Summary: hot topic knowledge shorttexts 
Home-page: UNKNOWN
Author: Yan Xing
Author-email: UNKNOWN
License: UNKNOWN
Platform: UNKNOWN
